{
    "name": "Maria Eduarda Abreu",
    "photo": "https://avatars.githubusercontent.com/u/137839112?s=400&u=c6d9ec46b7905dab4ec119237b79b0dc79047526&v=4",
    "job": "Developer FullStack Jr",
    "location": "Belo Horizonte - BR",
    "phone": "(31) 9 7338-4925",
    "email": "contato.mariaeduardaabreu@gmail.com",
    "skills": {
      "hardSkills": [
        {
          "name": "javascript",
          "logo": "https://raw.githubusercontent.com/MariaAbreu005/portifolio/main/data/img/js.png"
        },
        {
          "name": "node.js",
          "logo": "https://raw.githubusercontent.com/MariaAbreu005/portifolio/main/data/img/nodejs.png"
        },
        {
          "name": "python",
          "logo": "https://raw.githubusercontent.com/MariaAbreu005/portifolio/main/data/img/py.png"
        },
        {
          "name": "csharp",
          "logo": "https://raw.githubusercontent.com/MariaAbreu005/portifolio/main/data/img/csharp.png"
        },
        {
          "name": ".net",
          "logo": "https://raw.githubusercontent.com/MariaAbreu005/portifolio/main/data/img/net.png"
        } 
      ],
      "softSkills": [
        "comunicação",
        "adaptabilidade",
        "Trabalho em equipe",
        "Flexibilidade",
        "Organização"
      ]
    },
    "languages": [
      "Português BR",
      "Inglês B2"

    ],
    "portfolio": [
      {
        "name": "Análise e Desenvolvimento De Software, FIAP- 06/2026",
        "url": ".",
        "github": true
      },
      {
        "name": "Curso Ministrado na DIO para a criação de uma página de portfolio",
        "url": "https://github.com/MariaAbreu005/portifolio.git",
        "github": true
      }
    ],
    "professionalExperience": [
      {
        "name": "Tec Celulares",
        "period": "10 meses",
        "description": ""
      }
    ]
  }
